{
    "cycle":17,
    "frozen":864666666,
    "frozenminusfee":804139999,
    "pendingminusfee":254,
    "pending":19180254,
    "paid":254819746,
    "deleguees":{
        "tz1LUZNxLonRmotkLszDcNQLBMkMj42x7DdY":{
            "address":"tz1LUZNxLonRmotkLszDcNQLBMkMj42x7DdY",
            "frozen":58464838,
            "pending":0,
            "paid":28017810,
            "alias":"Greasy Kid Tezos",
            "cycles":{
                "14":{
                    "cycle":14,
                    "percentage":100.0,
                    "balance":"10715111700",
                    "frozen":0,
                    "reward":7440000
                },
                "15":{
                    "cycle":15,
                    "percentage":8.7179,
                    "balance":"10715111700",
                    "frozen":0,
                    "reward":324305
                },
                "16":{
                    "cycle":16,
                    "percentage":8.3122,
                    "balance":"10715111700",
                    "frozen":0,
                    "reward":10049449
                },
                "17":{
                    "cycle":17,
                    "percentage":8.3122,
                    "balance":"10715111700",
                    "frozen":0,
                    "reward":10204056
                },
                "18":{
                    "cycle":18,
                    "percentage":6.7429,
                    "balance":"10715111700",
                    "frozen":10660524,
                    "reward":0
                },
                "19":{
                    "cycle":19,
                    "percentage":11.0414,
                    "balance":"18393614389",
                    "frozen":13862477,
                    "reward":0
                },
                "20":{
                    "cycle":20,
                    "percentage":6.5185,
                    "balance":"18393614389",
                    "frozen":8850819,
                    "reward":0
                },
                "21":{
                    "cycle":21,
                    "percentage":6.5213,
                    "balance":"18401614389",
                    "frozen":11462489,
                    "reward":0
                },
                "22":{
                    "cycle":22,
                    "percentage":6.5227,
                    "balance":"18405614389",
                    "frozen":13628529,
                    "reward":0
                }
            }
        },
        "KT1TTStyYu6EWsUCwN6mVmq2q78cV6dH3CWi":{
            "address":"KT1TTStyYu6EWsUCwN6mVmq2q78cV6dH3CWi",
            "frozen":359313751,
            "pending":0,
            "paid":192044894,
            "alias":"flaco",
            "cycles":{
                "15":{
                    "cycle":15,
                    "percentage":81.3609,
                    "balance":"100000000000",
                    "frozen":0,
                    "reward":3026625
                },
                "16":{
                    "cycle":16,
                    "percentage":77.5746,
                    "balance":"100000000000",
                    "frozen":0,
                    "reward":93787691
                },
                "17":{
                    "cycle":17,
                    "percentage":77.5746,
                    "balance":"100000000000",
                    "frozen":0,
                    "reward":95230578
                },
                "18":{
                    "cycle":18,
                    "percentage":62.9295,
                    "balance":"100000000000",
                    "frozen":99491539,
                    "reward":0
                },
                "19":{
                    "cycle":19,
                    "percentage":60.0289,
                    "balance":"100000000000",
                    "frozen":75366283,
                    "reward":0
                },
                "20":{
                    "cycle":20,
                    "percentage":35.4389,
                    "balance":"100000000000",
                    "frozen":48118938,
                    "reward":0
                },
                "21":{
                    "cycle":21,
                    "percentage":35.4389,
                    "balance":"100000000000",
                    "frozen":62290954,
                    "reward":0
                },
                "22":{
                    "cycle":22,
                    "percentage":35.4389,
                    "balance":"100000000000",
                    "frozen":74046037,
                    "reward":0
                }
            }
        },
        "KT1KN7NwY7Q1FXvgEq8cradTLed1JCuY7Uk4":{
            "address":"KT1KN7NwY7Q1FXvgEq8cradTLed1JCuY7Uk4",
            "frozen":43814548,
            "pending":0,
            "paid":23417837,
            "alias":"rorro",
            "cycles":{
                "15":{
                    "cycle":15,
                    "percentage":9.9211,
                    "balance":"12194000000",
                    "frozen":0,
                    "reward":369064
                },
                "16":{
                    "cycle":16,
                    "percentage":9.4594,
                    "balance":"12194000000",
                    "frozen":0,
                    "reward":11436414
                },
                "17":{
                    "cycle":17,
                    "percentage":9.4594,
                    "balance":"12194000000",
                    "frozen":0,
                    "reward":11612359
                },
                "18":{
                    "cycle":18,
                    "percentage":7.6736,
                    "balance":"12194000000",
                    "frozen":12131961,
                    "reward":0
                },
                "19":{
                    "cycle":19,
                    "percentage":7.3199,
                    "balance":"12194000000",
                    "frozen":9190134,
                    "reward":0
                },
                "20":{
                    "cycle":20,
                    "percentage":4.3214,
                    "balance":"12194000000",
                    "frozen":5867596,
                    "reward":0
                },
                "21":{
                    "cycle":21,
                    "percentage":4.3214,
                    "balance":"12194000000",
                    "frozen":7595724,
                    "reward":0
                },
                "22":{
                    "cycle":22,
                    "percentage":4.3214,
                    "balance":"12194000000",
                    "frozen":9029133,
                    "reward":0
                }
            }
        },
        "KT1LzQkEma9Y8XK7ZoJj3LDR3A3hPmJMWnxb":{
            "address":"KT1LzQkEma9Y8XK7ZoJj3LDR3A3hPmJMWnxb",
            "frozen":21554710,
            "pending":0,
            "paid":11339205,
            "alias":"mario",
            "cycles":{
                "16":{
                    "cycle":16,
                    "percentage":4.6537,
                    "balance":"5999000000",
                    "frozen":0,
                    "reward":5626323
                },
                "17":{
                    "cycle":17,
                    "percentage":4.6537,
                    "balance":"5999000000",
                    "frozen":0,
                    "reward":5712882
                },
                "18":{
                    "cycle":18,
                    "percentage":3.7751,
                    "balance":"5999000000",
                    "frozen":5968433,
                    "reward":0
                },
                "19":{
                    "cycle":19,
                    "percentage":3.6011,
                    "balance":"5999000000",
                    "frozen":4521181,
                    "reward":0
                },
                "20":{
                    "cycle":20,
                    "percentage":2.1259,
                    "balance":"5999000000",
                    "frozen":2886547,
                    "reward":0
                },
                "21":{
                    "cycle":21,
                    "percentage":2.1259,
                    "balance":"5999000000",
                    "frozen":3736694,
                    "reward":0
                },
                "22":{
                    "cycle":22,
                    "percentage":2.1259,
                    "balance":"5999000000",
                    "frozen":4441855,
                    "reward":0
                }
            }
        },
        "KT19NaLNhx8Htb5YE9rJLkC1bE5Uc6tPEaP6":{
            "address":"KT19NaLNhx8Htb5YE9rJLkC1bE5Uc6tPEaP6",
            "frozen":107792629,
            "pending":0,
            "paid":0,
            "alias":"moi",
            "cycles":{
                "18":{
                    "cycle":18,
                    "percentage":18.8786,
                    "balance":"29999730000",
                    "frozen":29847066,
                    "reward":0
                },
                "19":{
                    "cycle":19,
                    "percentage":18.0085,
                    "balance":"29999730000",
                    "frozen":22609671,
                    "reward":0
                },
                "20":{
                    "cycle":20,
                    "percentage":10.6315,
                    "balance":"29999730000",
                    "frozen":14435450,
                    "reward":0
                },
                "21":{
                    "cycle":21,
                    "percentage":10.6315,
                    "balance":"29999730000",
                    "frozen":18686987,
                    "reward":0
                },
                "22":{
                    "cycle":22,
                    "percentage":10.6315,
                    "balance":"29999730000",
                    "frozen":22213455,
                    "reward":0
                }
            }
        },
        "KT1X3vBqbTuq7yP4hLrpfTThhYD4tEsDRFNb":{
            "address":"KT1X3vBqbTuq7yP4hLrpfTThhYD4tEsDRFNb",
            "frozen":22601235,
            "pending":0,
            "paid":0,
            "alias":"dmp",
            "cycles":{
                "20":{
                    "cycle":20,
                    "percentage":4.3423,
                    "balance":"12253000000",
                    "frozen":5895974,
                    "reward":0
                },
                "21":{
                    "cycle":21,
                    "percentage":4.3423,
                    "balance":"12253000000",
                    "frozen":7632460,
                    "reward":0
                },
                "22":{
                    "cycle":22,
                    "percentage":4.3423,
                    "balance":"12253000000",
                    "frozen":9072801,
                    "reward":0
                }
            }
        },
        "KT1PLhbTgZdXLM2YjC6EVXUxXAYAp2JMBYwZ":{
            "address":"KT1PLhbTgZdXLM2YjC6EVXUxXAYAp2JMBYwZ",
            "frozen":184455929,
            "pending":0,
            "paid":0,
            "alias":"cassis",
            "cycles":{
                "20":{
                    "cycle":20,
                    "percentage":35.4389,
                    "balance":"100000000000",
                    "frozen":48118938,
                    "reward":0
                },
                "21":{
                    "cycle":21,
                    "percentage":35.4389,
                    "balance":"100000000000",
                    "frozen":62290954,
                    "reward":0
                },
                "22":{
                    "cycle":22,
                    "percentage":35.4389,
                    "balance":"100000000000",
                    "frozen":74046037,
                    "reward":0
                }
            }
        },
        "KT1AW3izX4R4dcwnJ1ZfkuChkM6UmyH8jBwy":{
            "address":"KT1AW3izX4R4dcwnJ1ZfkuChkM6UmyH8jBwy",
            "frozen":6153231,
            "pending":0,
            "paid":0,
            "alias":"santi",
            "cycles":{
                "20":{
                    "cycle":20,
                    "percentage":1.1822,
                    "balance":"3336000000",
                    "frozen":1605191,
                    "reward":0
                },
                "21":{
                    "cycle":21,
                    "percentage":1.1822,
                    "balance":"3336000000",
                    "frozen":2077952,
                    "reward":0
                },
                "22":{
                    "cycle":22,
                    "percentage":1.1822,
                    "balance":"3336000000",
                    "frozen":2470088,
                    "reward":0
                }
            }
        }
    },
    "cycles":{
        "14":{
            "frozenminusfee":0,
            "frozen":0,
            "rewardminusfee":7440000,
            "reward":8000000
        },
        "15":{
            "frozenminusfee":0,
            "frozen":0,
            "rewardminusfee":3720000,
            "reward":4000000
        },
        "16":{
            "frozenminusfee":0,
            "frozen":0,
            "rewardminusfee":120900000,
            "reward":130000000
        },
        "17":{
            "frozenminusfee":0,
            "frozen":0,
            "rewardminusfee":122760000,
            "reward":132000000
        },
        "18":{
            "frozenminusfee":158100000,
            "frozen":170000000,
            "rewardminusfee":0,
            "reward":0
        },
        "19":{
            "frozenminusfee":125550000,
            "frozen":135000000,
            "rewardminusfee":0,
            "reward":0
        },
        "20":{
            "frozenminusfee":135780000,
            "frozen":146000000,
            "rewardminusfee":0,
            "reward":0
        },
        "21":{
            "frozenminusfee":175770000,
            "frozen":189000000,
            "rewardminusfee":0,
            "reward":0
        },
        "22":{
            "frozenminusfee":208939999,
            "frozen":224666666,
            "rewardminusfee":0,
            "reward":0
        }
    }
}